aiovantage/__init__.py
aiovantage/_connection.py
aiovantage/_logger.py
aiovantage/command_client.py
aiovantage/config_client.py
aiovantage/controllers.py
aiovantage/discovery.py
aiovantage/errors.py
aiovantage/events.py
aiovantage/object_interfaces.py
aiovantage/objects.py
aiovantage/py.typed
aiovantage/_command_client/__init__.py
aiovantage/_command_client/client.py
aiovantage/_command_client/connection.py
aiovantage/_command_client/converter.py
aiovantage/_command_client/events.py
aiovantage/_config_client/__init__.py
aiovantage/_config_client/client.py
aiovantage/_config_client/connection.py
aiovantage/_config_client/interfaces/__init__.py
aiovantage/_config_client/interfaces/configuration.py
aiovantage/_config_client/interfaces/introspection.py
aiovantage/_config_client/interfaces/login.py
aiovantage/_controllers/__init__.py
aiovantage/_controllers/anemo_sensors.py
aiovantage/_controllers/areas.py
aiovantage/_controllers/back_boxes.py
aiovantage/_controllers/base.py
aiovantage/_controllers/blind_groups.py
aiovantage/_controllers/blinds.py
aiovantage/_controllers/buttons.py
aiovantage/_controllers/dry_contacts.py
aiovantage/_controllers/gmem.py
aiovantage/_controllers/light_sensors.py
aiovantage/_controllers/load_groups.py
aiovantage/_controllers/loads.py
aiovantage/_controllers/masters.py
aiovantage/_controllers/modules.py
aiovantage/_controllers/omni_sensors.py
aiovantage/_controllers/port_devices.py
aiovantage/_controllers/power_profiles.py
aiovantage/_controllers/query.py
aiovantage/_controllers/rgb_loads.py
aiovantage/_controllers/stations.py
aiovantage/_controllers/tasks.py
aiovantage/_controllers/temperatures.py
aiovantage/_controllers/thermostats.py
aiovantage/_object_interfaces/__init__.py
aiovantage/_object_interfaces/anemo_sensor.py
aiovantage/_object_interfaces/base.py
aiovantage/_object_interfaces/blind.py
aiovantage/_object_interfaces/button.py
aiovantage/_object_interfaces/color_temperature.py
aiovantage/_object_interfaces/configuration.py
aiovantage-0.22.6.dist-info/METADATA
aiovantage-0.22.6.dist-info/WHEEL
aiovantage-0.22.6.dist-info/licenses/LICENSE
aiovantage-0.22.6.dist-info/RECORD
