Metadata-Version: 2.4
Name: aiovantage
Version: 0.22.6
Summary: Interact with and control Vantage InFusion home automation controllers.
Project-URL: Documentation, https://github.com/loopj/aiovantage#readme
Project-URL: Issues, https://github.com/loopj/aiovantage/issues
Project-URL: Source, https://github.com/loopj/aiovantage
Author-email: James Smith <james@loopj.com>
License-Expression: MIT
License-File: LICENSE
Classifier: Intended Audience :: Developers
Classifier: Operating System :: OS Independent
Classifier: Programming Language :: Python
Classifier: Programming Language :: Python :: 3
Classifier: Topic :: Home Automation
Classifier: Topic :: Software Development :: Libraries :: Python Modules
Requires-Python: >=3.10
Requires-Dist: typing-extensions<5.0,>=4.6.3
Requires-Dist: xsdata==25.4
Provides-Extra: dev
Requires-Dist: bumpver==2024.1130; extra == 'dev'
Requires-Dist: pyright==1.1.407; extra == 'dev'
Requires-Dist: ruff==0.14.10; extra == 'dev'
Provides-Extra: docs
Requires-Dist: mkdocs-api-autonav==0.4.0; extra == 'docs'
Requires-Dist: mkdocs-material==9.7.1; extra == 'docs'
Requires-Dist: mkdocs==1.6.1; extra == 'docs'
Requires-Dist: mkdocstrings-python==2.0.1; extra == 'docs'
Requires-Dist: mkdocstrings==0.30.1; extra == 'docs'
